drive/__init__.py
drive/auth.py
drive/client.py
drive/exceptions.py
drive/files.py
drive/mimetypes.py
drive/py.typed
drive/sheets.py
drive-0.4.3.dist-info/LICENSE
drive-0.4.3.dist-info/METADATA
drive-0.4.3.dist-info/WHEEL
drive-0.4.3.dist-info/RECORD
