Metadata-Version: 2.1
Name: drive
Version: 0.4.3
Summary: Google Drive client
License: MIT
Author: Baptiste Fontaine
Author-email: b@ptistefontaine.fr
Requires-Python: >=3.9,<4.0
Classifier: Development Status :: 5 - Production/Stable
Classifier: License :: OSI Approved :: MIT License
Classifier: Programming Language :: Python :: 3
Classifier: Programming Language :: Python :: 3.9
Classifier: Programming Language :: Python :: 3.10
Classifier: Programming Language :: Python :: 3.11
Requires-Dist: google-api-python-client (>=2.64.0,<3.0.0)
Requires-Dist: httplib2 (>=0.20.4,<0.21.0)
Requires-Dist: oauth2client (>=4.1.3,<5.0.0)
Requires-Dist: openpyxl (>=3.0.10,<4.0.0)
Requires-Dist: python-magic (>=0.4.27,<0.5.0)
Requires-Dist: python-magic-bin (>=0.4.14,<0.5.0) ; sys_platform == "windows"
